asterism/__init__.py
asterism/bagit_helpers.py
asterism/file_helpers.py
asterism/models.py
asterism/view_mixins.py
asterism/views.py
asterism/tests/__init__.py
asterism/tests/helpers.py
asterism/tests/test_bagit.py
asterism/tests/test_file_helpers.py
asterism/tests/test_models.py
asterism/tests/test_views.py
asterism-1.1.0.dist-info/LICENSE
asterism-1.1.0.dist-info/METADATA
asterism-1.1.0.dist-info/WHEEL
asterism-1.1.0.dist-info/top_level.txt
asterism-1.1.0.dist-info/RECORD
