Metadata-Version: 2.1
Name: asterism
Version: 1.1.0
Summary: Helpers for Project Electron infrastructure
Home-page: http://github.com/RockefellerArchiveCenter/asterism
Author: Rockefeller Archive Center
Author-email: archive@rockarch.org
License: MIT
License-File: LICENSE
Requires-Dist: bagit
Requires-Dist: django
Requires-Dist: djangorestframework
